aws_ec2_pricing_tool/__init__.py
aws_ec2_pricing_tool/cli.py
aws_ec2_pricing_tool-0.1.6.dist-info/licenses/LICENSE
aws_ec2_pricing_tool-0.1.6.dist-info/METADATA
aws_ec2_pricing_tool-0.1.6.dist-info/WHEEL
aws_ec2_pricing_tool-0.1.6.dist-info/entry_points.txt
aws_ec2_pricing_tool-0.1.6.dist-info/top_level.txt
aws_ec2_pricing_tool-0.1.6.dist-info/RECORD
