Metadata-Version: 2.4
Name: aws-ec2-pricing-tool
Version: 0.1.6
Summary: CLI tool to compare AWS EC2 on-demand pricing and AMIs across regions
Home-page: https://github.com/spithash/AWS-EC2-Instance-Pricing-Tool
Author: Stathis Xantinidis
Author-email: spithash@tuta.io
Classifier: Programming Language :: Python :: 3
Classifier: License :: OSI Approved :: GNU General Public License v3 (GPLv3)
Classifier: Operating System :: OS Independent
Requires-Python: >=3.7
License-File: LICENSE
Requires-Dist: boto3
Requires-Dist: rich
Dynamic: author
Dynamic: author-email
Dynamic: classifier
Dynamic: description
Dynamic: description-content-type
Dynamic: home-page
Dynamic: license-file
Dynamic: requires-dist
Dynamic: requires-python
Dynamic: summary
